README.rst
setup.cfg
setup.py
stayontop/__init__.py
stayontop/stayontop.py
stayontop.egg-info/PKG-INFO
stayontop.egg-info/SOURCES.txt
stayontop.egg-info/dependency_links.txt
stayontop.egg-info/entry_points.txt
stayontop.egg-info/requires.txt
stayontop.egg-info/top_level.txt