Metadata-Version: 1.0
Name: stayontop
Version: 0.1a0
Summary: Keep AWS instances stopped on out of office hours
Home-page: https://github.com/guraslan/stayontop
Author: Yagmur Guraslan
Author-email: guraslan@gmail.com
License: BSD
Download-URL: https://github.com/guraslan/stayontop/tarball/0.1a0
Keywords: stayontop keep stopped aws instances cost effective
Platform: UNKNOWN
Classifier: Development Status :: 3 - Alpha
Classifier: Environment :: Console
Classifier: Intended Audience :: System Administrators
Classifier: Programming Language :: Python :: 2
Classifier: Programming Language :: Python :: 2.6
Classifier: Programming Language :: Python :: 2.7
Classifier: Topic :: System :: Systems Administration
